{
    "Escrow_ABI": [
        {
            "inputs": [
                {
                    "internalType": "address",
                    "name": "_seller",
                    "type": "address"
                },
                {
                    "internalType": "address",
                    "name": "_arbiter",
                    "type": "address"
                }
            ],
            "stateMutability": "payable",
            "type": "constructor"
        },
        {
            "inputs": [],
            "name": "amount",
            "outputs": [
                {
                    "internalType": "uint256",
                    "name": "",
                    "type": "uint256"
                }
            ],
            "stateMutability": "view",
            "type": "function"
        },
        {
            "inputs": [],
            "name": "approve",
            "outputs": [],
            "stateMutability": "nonpayable",
            "type": "function"
        },
        {
            "inputs": [
                {
                    "internalType": "address",
                    "name": "",
                    "type": "address"
                }
            ],
            "name": "approved",
            "outputs": [
                {
                    "internalType": "bool",
                    "name": "",
                    "type": "bool"
                }
            ],
            "stateMutability": "view",
            "type": "function"
        },
        {
            "inputs": [],
            "name": "arbiter",
            "outputs": [
                {
                    "internalType": "address",
                    "name": "",
                    "type": "address"
                }
            ],
            "stateMutability": "view",
            "type": "function"
        },
        {
            "inputs": [],
            "name": "buyer",
            "outputs": [
                {
                    "internalType": "address",
                    "name": "",
                    "type": "address"
                }
            ],
            "stateMutability": "view",
            "type": "function"
        },
        {
            "inputs": [],
            "name": "dispute",
            "outputs": [],
            "stateMutability": "nonpayable",
            "type": "function"
        },
        {
            "inputs": [],
            "name": "resolve",
            "outputs": [],
            "stateMutability": "nonpayable",
            "type": "function"
        },
        {
            "inputs": [],
            "name": "seller",
            "outputs": [
                {
                    "internalType": "address",
                    "name": "",
                    "type": "address"
                }
            ],
            "stateMutability": "view",
            "type": "function"
        },
        {
            "inputs": [],
            "name": "signAndReleaseFund",
            "outputs": [],
            "stateMutability": "nonpayable",
            "type": "function"
        },
        {
            "inputs": [
                {
                    "internalType": "address",
                    "name": "",
                    "type": "address"
                }
            ],
            "name": "signed",
            "outputs": [
                {
                    "internalType": "bool",
                    "name": "",
                    "type": "bool"
                }
            ],
            "stateMutability": "view",
            "type": "function"
        },
        {
            "inputs": [],
            "name": "state",
            "outputs": [
                {
                    "internalType": "enum States",
                    "name": "",
                    "type": "uint8"
                }
            ],
            "stateMutability": "view",
            "type": "function"
        }
    ],
    "Escrow_ADDRESS": "0x8097367eE60F80Ad88a9f065F381B1Ca9a330342",
    "Escrow_CHAINID": 31337
}